torch_loops/__init__.py
torch_loops/prelude.py
torch_loops/torch_loops.py
torch_loops/types.py
torch_loops-0.4.0.dist-info/WHEEL
torch_loops-0.4.0.dist-info/METADATA
torch_loops-0.4.0.dist-info/RECORD
