Metadata-Version: 2.1
Name: torch-loops
Version: 0.4.0
Summary: simple loops for pytorch
License: MIT
Author: yohan-pg
Author-email: pg.yohan@gmail.com
Requires-Python: >=3.10,<4.0
Classifier: License :: OSI Approved :: MIT License
Classifier: Programming Language :: Python :: 3
Classifier: Programming Language :: Python :: 3.10
